MANIFEST.in
README
README.rst
setup.py
apikey/__init__.py
apikey/auth.py
apikey/models.py
django_apikey.egg-info/PKG-INFO
django_apikey.egg-info/SOURCES.txt
django_apikey.egg-info/dependency_links.txt
django_apikey.egg-info/top_level.txt