Metadata-Version: 1.0
Name: django-apikey
Version: 0.1.8
Summary: Simple Key authentication for Django.Based on  github.com/scoursen/django-apikey
Home-page: https://www.github.com/jorgeecardona/django-apikey
Author: Jorge Eduardo Cardona
Author-email: jorgeecardona@gmail.com
License: BSD
Keywords: django authentication piston
Platform: UNKNOWN
Classifier: License :: OSI Approved :: BSD License
